agora/__init__.py
agora/blockchain_utils.py
agora/client.py
agora/exceptions.py
agora/ipfs_utils.py
agora/test.py
agora_demo/__init__.py
agora_demo/core/__init__.py
agora_demo/core/configuration.py
agora_demo/core/dataset_manager.py
agora_demo/core/developer.py
agora_demo/core/fed_learning.py
agora_demo/core/listener.py
agora_demo/core/runner.py
agora_demo/core/scheduler.py
agora_demo/core/blockchain/__init__.py
agora_demo/core/blockchain/blockchain_utils.py
agora_demo/core/blockchain/client.py
agora_demo/core/blockchain/ipfs_utils.py
agora_demo-0.1.0.dist-info/METADATA
agora_demo-0.1.0.dist-info/RECORD
agora_demo-0.1.0.dist-info/WHEEL
agora_demo-0.1.0.dist-info/top_level.txt
agora_dp/__init__.py
agora_dp/application.py
agora_dp/blockchain_utils.py
agora_dp/client.py
agora_dp/exceptions.py
agora_dp/ipfs_utils.py
agora_dp/test.py
agora_mt/__init__.py
agora_mt/application.py
agora_mt/blockchain_utils.py
agora_mt/client.py
agora_mt/exceptions.py
agora_mt/ipfs_utils.py
agora_mt/test.py
agora_pkg/__init__.py
agora_pkg/blockchain_utils.py
agora_pkg/client.py
agora_pkg/exceptions.py
agora_pkg/ipfs_utils.py
agora_pkg/test.py
