Metadata-Version: 2.1
Name: agora-demo
Version: 0.1.0
Summary: A demo testing configuration and dataset management.
Home-page: UNKNOWN
Author: Neelesh Dodda
Author-email: ndodda@berkeley.edu
License: UNKNOWN
Platform: UNKNOWN
